krank/__init__.py
krank/_corpus.py
krank/_registry.py
krank/_schemas.py
krank/data/registry-schema.yaml
krank/data/registry.yaml
krank-0.1.0.dist-info/licenses/LICENSE.txt
krank-0.1.0.dist-info/METADATA
krank-0.1.0.dist-info/WHEEL
krank-0.1.0.dist-info/top_level.txt
krank-0.1.0.dist-info/RECORD
