Metadata-Version: 2.4
Name: krank
Version: 0.1.0
Summary: Fetch dream reports.
Author-email: Remington Mallett <mallett.remy@gmail.com>
Maintainer-email: Remington Mallett <mallett.remy@gmail.com>
Project-URL: Homepage, https://remrama.github.io/krank
Project-URL: Source, https://github.com/remrama/krank
Keywords: sleep,dreams,data,datasets,text,nlp
Classifier: Development Status :: 3 - Alpha
Classifier: License :: OSI Approved :: MIT License
Classifier: Operating System :: OS Independent
Classifier: Intended Audience :: Science/Research
Classifier: Topic :: Scientific/Engineering
Classifier: Programming Language :: Python
Classifier: Programming Language :: Python :: 3
Classifier: Programming Language :: Python :: 3.11
Classifier: Programming Language :: Python :: 3.12
Classifier: Programming Language :: Python :: 3.13
Classifier: Programming Language :: Python :: 3.14
Requires-Python: >=3.11
License-File: LICENSE.txt
Requires-Dist: ftfy>=6.0
Requires-Dist: pandas>=2.0
Requires-Dist: pandera>=0.27
Requires-Dist: pooch>=1.8
Requires-Dist: pyyaml>=6.0
Provides-Extra: dev
Requires-Dist: ruff>=0.14; extra == "dev"
Requires-Dist: pytest>=8.0; extra == "dev"
Requires-Dist: pytest-cov>=6.0; extra == "dev"
Requires-Dist: jsonschema>=4.0; extra == "dev"
Provides-Extra: docs
Requires-Dist: mkdocs-material>=9.0; extra == "docs"
Requires-Dist: mkdocs-jupyter>=0.25; extra == "docs"
Dynamic: license-file
